dishook.py
xDisHook-1.0.2.dist-info/LICENSE
xDisHook-1.0.2.dist-info/METADATA
xDisHook-1.0.2.dist-info/WHEEL
xDisHook-1.0.2.dist-info/entry_points.txt
xDisHook-1.0.2.dist-info/top_level.txt
xDisHook-1.0.2.dist-info/RECORD
