Metadata-Version: 2.1
Name: xDisHook
Version: 1.0.2
Summary: A tool for generating and checking Discord Nitro codes
Home-page: https://github.com/im-hanzou/DisHook
Author: Hanzou
Author-email: hanzou@hanzou.sh
Classifier: Development Status :: 5 - Production/Stable
Classifier: Intended Audience :: Developers
Classifier: Topic :: Software Development :: Libraries :: Python Modules
Classifier: License :: OSI Approved :: MIT License
Classifier: Programming Language :: Python :: 3
Classifier: Programming Language :: Python :: 3.7
Classifier: Programming Language :: Python :: 3.8
Classifier: Programming Language :: Python :: 3.9
Requires-Python: >=3.7
License-File: LICENSE
Requires-Dist: requests
Requires-Dist: colorama
